[
  {
    "pixeles_validos": 158994,
    "pixeles_calientes": 1760,
    "fraccion_caliente": 0.01107,
    "max_nhiswir": 0.179973,
    "max_nhiswnir": -0.792756,
    "swir2_total": 131.7014,
    "thresh_swir": 0.151565,
    "thresh_swnir": -0.334033,
    "bg_median_swir": 0.076353,
    "bg_std_swir": 0.025071,
    "alerta": true,
    "fecha": "2026-03-23",
    "satelite": "landsat-9",
    "cloud_cover": 34.65,
    "sensor": "Landsat"
  },
  {
    "pixeles_validos": 159556,
    "pixeles_calientes": 0,
    "fraccion_caliente": 0.0,
    "max_nhiswir": 0.0,
    "max_nhiswnir": 0.0,
    "swir2_total": 0.0,
    "thresh_swir": 0.074821,
    "thresh_swnir": 0.153378,
    "bg_median_swir": -0.061666,
    "bg_std_swir": 0.045496,
    "alerta": false,
    "fecha": "2026-03-12",
    "satelite": "Sentinel-2A",
    "cloud_cover": 29.586509,
    "sensor": "Sentinel-2"
  },
  {
    "pixeles_validos": 158696,
    "pixeles_calientes": 26,
    "fraccion_caliente": 0.000164,
    "max_nhiswir": 0.21216,
    "max_nhiswnir": 0.602933,
    "swir2_total": 1.8784,
    "thresh_swir": 0.1808,
    "thresh_swnir": 0.163296,
    "bg_median_swir": -0.024236,
    "bg_std_swir": 0.068345,
    "alerta": true,
    "fecha": "2026-03-08",
    "satelite": "landsat-8",
    "cloud_cover": 38.55,
    "sensor": "Landsat"
  },
  {
    "pixeles_validos": 160000,
    "pixeles_calientes": 0,
    "fraccion_caliente": 0.0,
    "max_nhiswir": 0.0,
    "max_nhiswnir": 0.0,
    "swir2_total": 0.0,
    "thresh_swir": 0.156717,
    "thresh_swnir": 0.448389,
    "bg_median_swir": -0.045815,
    "bg_std_swir": 0.06751,
    "alerta": false,
    "fecha": "2026-03-05",
    "satelite": "Sentinel-2B",
    "cloud_cover": 29.837689,
    "sensor": "Sentinel-2"
  },
  {
    "pixeles_validos": 160000,
    "pixeles_calientes": 0,
    "fraccion_caliente": 0.0,
    "max_nhiswir": 0.0,
    "max_nhiswnir": 0.0,
    "swir2_total": 0.0,
    "thresh_swir": 0.15999,
    "thresh_swnir": 0.456603,
    "bg_median_swir": -0.049336,
    "bg_std_swir": 0.069776,
    "alerta": false,
    "fecha": "2026-02-21",
    "satelite": "Sentinel-2C",
    "cloud_cover": 7.959738,
    "sensor": "Sentinel-2"
  },
  {
    "pixeles_validos": 85076,
    "pixeles_calientes": 0,
    "fraccion_caliente": 0.0,
    "max_nhiswir": 0.0,
    "max_nhiswnir": 0.0,
    "swir2_total": 0.0,
    "thresh_swir": 0.224213,
    "thresh_swnir": 0.407945,
    "bg_median_swir": -0.157658,
    "bg_std_swir": 0.12729,
    "alerta": false,
    "fecha": "2026-02-20",
    "satelite": "landsat-8",
    "cloud_cover": 19.12,
    "sensor": "Landsat"
  },
  {
    "pixeles_validos": 159727,
    "pixeles_calientes": 0,
    "fraccion_caliente": 0.0,
    "max_nhiswir": 0.0,
    "max_nhiswnir": 0.0,
    "swir2_total": 0.0,
    "thresh_swir": 0.16449,
    "thresh_swnir": 0.551905,
    "bg_median_swir": -0.027276,
    "bg_std_swir": 0.063922,
    "alerta": false,
    "fecha": "2026-02-13",
    "satelite": "Sentinel-2B",
    "cloud_cover": 39.167243,
    "sensor": "Sentinel-2"
  }
]