[
  {
    "pixeles_validos": 160000,
    "pixeles_calientes": 0,
    "fraccion_caliente": 0.0,
    "max_nhiswir": 0.0,
    "max_nhiswnir": 0.0,
    "swir2_total": 0.0,
    "thresh_swir": 0.11652,
    "thresh_swnir": 0.432462,
    "bg_median_swir": -0.118099,
    "bg_std_swir": 0.078206,
    "alerta": false,
    "fecha": "2026-04-09",
    "satelite": "Sentinel-2C",
    "cloud_cover": 18.658656,
    "sensor": "Sentinel-2"
  },
  {
    "pixeles_validos": 59518,
    "pixeles_calientes": 0,
    "fraccion_caliente": 0.0,
    "max_nhiswir": 0.0,
    "max_nhiswnir": 0.0,
    "swir2_total": 0.0,
    "thresh_swir": 0.277132,
    "thresh_swnir": 0.30811,
    "bg_median_swir": -0.201964,
    "bg_std_swir": 0.159699,
    "alerta": false,
    "fecha": "2026-04-08",
    "satelite": "landsat-9",
    "cloud_cover": 39.32,
    "sensor": "Landsat"
  },
  {
    "pixeles_validos": 160000,
    "pixeles_calientes": 0,
    "fraccion_caliente": 0.0,
    "max_nhiswir": 0.0,
    "max_nhiswnir": 0.0,
    "swir2_total": 0.0,
    "thresh_swir": 0.128723,
    "thresh_swnir": 0.398009,
    "bg_median_swir": -0.101349,
    "bg_std_swir": 0.076691,
    "alerta": false,
    "fecha": "2026-04-07",
    "satelite": "Sentinel-2B",
    "cloud_cover": 34.332025,
    "sensor": "Sentinel-2"
  },
  {
    "pixeles_validos": 160000,
    "pixeles_calientes": 0,
    "fraccion_caliente": 0.0,
    "max_nhiswir": 0.0,
    "max_nhiswnir": 0.0,
    "swir2_total": 0.0,
    "thresh_swir": 0.121659,
    "thresh_swnir": 0.382199,
    "bg_median_swir": -0.110735,
    "bg_std_swir": 0.077465,
    "alerta": false,
    "fecha": "2026-04-04",
    "satelite": "Sentinel-2B",
    "cloud_cover": 0.136993,
    "sensor": "Sentinel-2"
  },
  {
    "pixeles_validos": 160000,
    "pixeles_calientes": 0,
    "fraccion_caliente": 0.0,
    "max_nhiswir": 0.0,
    "max_nhiswnir": 0.0,
    "swir2_total": 0.0,
    "thresh_swir": 0.103658,
    "thresh_swnir": 0.375657,
    "bg_median_swir": -0.118466,
    "bg_std_swir": 0.074041,
    "alerta": false,
    "fecha": "2026-04-02",
    "satelite": "Sentinel-2C",
    "cloud_cover": 4.507881,
    "sensor": "Sentinel-2"
  },
  {
    "pixeles_validos": 77299,
    "pixeles_calientes": 0,
    "fraccion_caliente": 0.0,
    "max_nhiswir": 0.0,
    "max_nhiswnir": 0.0,
    "swir2_total": 0.0,
    "thresh_swir": 0.269204,
    "thresh_swnir": 0.405102,
    "bg_median_swir": -0.072694,
    "bg_std_swir": 0.113966,
    "alerta": false,
    "fecha": "2026-04-01",
    "satelite": "landsat-9",
    "cloud_cover": 6.24,
    "sensor": "Landsat"
  },
  {
    "pixeles_validos": 107600,
    "pixeles_calientes": 125,
    "fraccion_caliente": 0.001162,
    "max_nhiswir": 0.108697,
    "max_nhiswnir": 0.984092,
    "swir2_total": 8.5741,
    "thresh_swir": 0.033412,
    "thresh_swnir": 0.077878,
    "bg_median_swir": -0.222661,
    "bg_std_swir": 0.085358,
    "alerta": true,
    "fecha": "2026-03-31",
    "satelite": "landsat-8",
    "cloud_cover": 46.57,
    "sensor": "Landsat",
    "hotspot_image": "2026-03-31_ls_hotspot.png"
  },
  {
    "pixeles_validos": 159699,
    "pixeles_calientes": 0,
    "fraccion_caliente": 0.0,
    "max_nhiswir": 0.0,
    "max_nhiswnir": 0.0,
    "swir2_total": 0.0,
    "thresh_swir": 0.169975,
    "thresh_swnir": 0.374441,
    "bg_median_swir": -0.060504,
    "bg_std_swir": 0.076826,
    "alerta": false,
    "fecha": "2026-03-30",
    "satelite": "Sentinel-2C",
    "cloud_cover": 25.692788,
    "sensor": "Sentinel-2"
  },
  {
    "pixeles_validos": 159824,
    "pixeles_calientes": 0,
    "fraccion_caliente": 0.0,
    "max_nhiswir": 0.0,
    "max_nhiswnir": 0.0,
    "swir2_total": 0.0,
    "thresh_swir": 0.11947,
    "thresh_swnir": 0.388471,
    "bg_median_swir": -0.10667,
    "bg_std_swir": 0.07538,
    "alerta": false,
    "fecha": "2026-03-28",
    "satelite": "Sentinel-2B",
    "cloud_cover": 2.357411,
    "sensor": "Sentinel-2"
  },
  {
    "pixeles_validos": 159023,
    "pixeles_calientes": 0,
    "fraccion_caliente": 0.0,
    "max_nhiswir": 0.0,
    "max_nhiswnir": 0.0,
    "swir2_total": 0.0,
    "thresh_swir": 0.158733,
    "thresh_swnir": 0.412549,
    "bg_median_swir": -0.024564,
    "bg_std_swir": 0.061099,
    "alerta": false,
    "fecha": "2026-03-25",
    "satelite": "Sentinel-2A",
    "cloud_cover": 40.236884,
    "sensor": "Sentinel-2"
  },
  {
    "pixeles_validos": 92908,
    "pixeles_calientes": 0,
    "fraccion_caliente": 0.0,
    "max_nhiswir": 0.0,
    "max_nhiswnir": 0.0,
    "swir2_total": 0.0,
    "thresh_swir": 0.197345,
    "thresh_swnir": 0.244457,
    "bg_median_swir": -0.08446,
    "bg_std_swir": 0.093935,
    "alerta": false,
    "fecha": "2026-03-24",
    "satelite": "landsat-8",
    "cloud_cover": 43.75,
    "sensor": "Landsat"
  },
  {
    "pixeles_validos": 159698,
    "pixeles_calientes": 0,
    "fraccion_caliente": 0.0,
    "max_nhiswir": 0.0,
    "max_nhiswnir": 0.0,
    "swir2_total": 0.0,
    "thresh_swir": 0.109227,
    "thresh_swnir": 0.375599,
    "bg_median_swir": -0.064364,
    "bg_std_swir": 0.057864,
    "alerta": false,
    "fecha": "2026-03-13",
    "satelite": "Sentinel-2C",
    "cloud_cover": 23.381828,
    "sensor": "Sentinel-2"
  },
  {
    "pixeles_validos": 159888,
    "pixeles_calientes": 0,
    "fraccion_caliente": 0.0,
    "max_nhiswir": 0.0,
    "max_nhiswnir": 0.0,
    "swir2_total": 0.0,
    "thresh_swir": 0.100316,
    "thresh_swnir": 0.349408,
    "bg_median_swir": -0.057814,
    "bg_std_swir": 0.05271,
    "alerta": false,
    "fecha": "2026-03-12",
    "satelite": "Sentinel-2A",
    "cloud_cover": 34.438667,
    "sensor": "Sentinel-2"
  },
  {
    "pixeles_validos": 160000,
    "pixeles_calientes": 0,
    "fraccion_caliente": 0.0,
    "max_nhiswir": 0.0,
    "max_nhiswnir": 0.0,
    "swir2_total": 0.0,
    "thresh_swir": 0.11327,
    "thresh_swnir": 0.296076,
    "bg_median_swir": -0.138013,
    "bg_std_swir": 0.083761,
    "alerta": false,
    "fecha": "2026-03-10",
    "satelite": "Sentinel-2C",
    "cloud_cover": 0.142709,
    "sensor": "Sentinel-2"
  },
  {
    "pixeles_validos": 160000,
    "pixeles_calientes": 0,
    "fraccion_caliente": 0.0,
    "max_nhiswir": 0.0,
    "max_nhiswnir": 0.0,
    "swir2_total": 0.0,
    "thresh_swir": 0.122772,
    "thresh_swnir": 0.284851,
    "bg_median_swir": -0.117047,
    "bg_std_swir": 0.079939,
    "alerta": false,
    "fecha": "2026-03-08",
    "satelite": "Sentinel-2B",
    "cloud_cover": 0.09968,
    "sensor": "Sentinel-2"
  },
  {
    "pixeles_validos": 160000,
    "pixeles_calientes": 0,
    "fraccion_caliente": 0.0,
    "max_nhiswir": 0.0,
    "max_nhiswnir": 0.0,
    "swir2_total": 0.0,
    "thresh_swir": 0.122401,
    "thresh_swnir": 0.311294,
    "bg_median_swir": -0.127413,
    "bg_std_swir": 0.083271,
    "alerta": false,
    "fecha": "2026-03-05",
    "satelite": "Sentinel-2B",
    "cloud_cover": 4.352748,
    "sensor": "Sentinel-2"
  },
  {
    "pixeles_validos": 160000,
    "pixeles_calientes": 0,
    "fraccion_caliente": 0.0,
    "max_nhiswir": 0.0,
    "max_nhiswnir": 0.0,
    "swir2_total": 0.0,
    "thresh_swir": 0.110371,
    "thresh_swnir": 0.296349,
    "bg_median_swir": -0.13682,
    "bg_std_swir": 0.082397,
    "alerta": false,
    "fecha": "2026-02-21",
    "satelite": "Sentinel-2C",
    "cloud_cover": 18.799651,
    "sensor": "Sentinel-2"
  },
  {
    "pixeles_validos": 66753,
    "pixeles_calientes": 0,
    "fraccion_caliente": 0.0,
    "max_nhiswir": 0.0,
    "max_nhiswnir": 0.0,
    "swir2_total": 0.0,
    "thresh_swir": 0.388189,
    "thresh_swnir": 0.44864,
    "bg_median_swir": -0.125139,
    "bg_std_swir": 0.171109,
    "alerta": false,
    "fecha": "2026-02-20",
    "satelite": "landsat-8",
    "cloud_cover": 2.25,
    "sensor": "Landsat"
  },
  {
    "pixeles_validos": 54104,
    "pixeles_calientes": 0,
    "fraccion_caliente": 0.0,
    "max_nhiswir": 0.0,
    "max_nhiswnir": 0.0,
    "swir2_total": 0.0,
    "thresh_swir": 0.379488,
    "thresh_swnir": 0.371814,
    "bg_median_swir": -0.101409,
    "bg_std_swir": 0.160299,
    "alerta": false,
    "fecha": "2026-02-19",
    "satelite": "landsat-9",
    "cloud_cover": 1.28,
    "sensor": "Landsat"
  },
  {
    "pixeles_validos": 160000,
    "pixeles_calientes": 0,
    "fraccion_caliente": 0.0,
    "max_nhiswir": 0.0,
    "max_nhiswnir": 0.0,
    "swir2_total": 0.0,
    "thresh_swir": 0.104437,
    "thresh_swnir": 0.234632,
    "bg_median_swir": -0.08785,
    "bg_std_swir": 0.064096,
    "alerta": false,
    "fecha": "2026-02-18",
    "satelite": "Sentinel-2C",
    "cloud_cover": 24.802195,
    "sensor": "Sentinel-2"
  },
  {
    "pixeles_validos": 159942,
    "pixeles_calientes": 0,
    "fraccion_caliente": 0.0,
    "max_nhiswir": 0.0,
    "max_nhiswnir": 0.0,
    "swir2_total": 0.0,
    "thresh_swir": 0.135047,
    "thresh_swnir": 0.310152,
    "bg_median_swir": -0.104116,
    "bg_std_swir": 0.079721,
    "alerta": false,
    "fecha": "2026-02-16",
    "satelite": "Sentinel-2B",
    "cloud_cover": 0.292557,
    "sensor": "Sentinel-2"
  },
  {
    "pixeles_validos": 160000,
    "pixeles_calientes": 0,
    "fraccion_caliente": 0.0,
    "max_nhiswir": 0.0,
    "max_nhiswnir": 0.0,
    "swir2_total": 0.0,
    "thresh_swir": 0.11738,
    "thresh_swnir": 0.351918,
    "bg_median_swir": -0.134363,
    "bg_std_swir": 0.083914,
    "alerta": false,
    "fecha": "2026-02-13",
    "satelite": "Sentinel-2B",
    "cloud_cover": 5.793674,
    "sensor": "Sentinel-2"
  },
  {
    "pixeles_validos": 92457,
    "pixeles_calientes": 0,
    "fraccion_caliente": 0.0,
    "max_nhiswir": 0.0,
    "max_nhiswnir": 0.0,
    "swir2_total": 0.0,
    "thresh_swir": 0.195196,
    "thresh_swnir": 0.385735,
    "bg_median_swir": -0.109039,
    "bg_std_swir": 0.101411,
    "alerta": false,
    "fecha": "2026-02-12",
    "satelite": "landsat-9",
    "cloud_cover": 16.87,
    "sensor": "Landsat"
  },
  {
    "pixeles_validos": 159990,
    "pixeles_calientes": 0,
    "fraccion_caliente": 0.0,
    "max_nhiswir": 0.0,
    "max_nhiswnir": 0.0,
    "swir2_total": 0.0,
    "thresh_swir": 0.170014,
    "thresh_swnir": 0.408031,
    "bg_median_swir": -0.071518,
    "bg_std_swir": 0.080511,
    "alerta": false,
    "fecha": "2026-02-08",
    "satelite": "Sentinel-2C",
    "cloud_cover": 15.90696,
    "sensor": "Sentinel-2"
  },
  {
    "pixeles_validos": 159998,
    "pixeles_calientes": 0,
    "fraccion_caliente": 0.0,
    "max_nhiswir": 0.0,
    "max_nhiswnir": 0.0,
    "swir2_total": 0.0,
    "thresh_swir": 0.145408,
    "thresh_swnir": 0.300896,
    "bg_median_swir": -0.095053,
    "bg_std_swir": 0.080153,
    "alerta": false,
    "fecha": "2026-02-06",
    "satelite": "Sentinel-2B",
    "cloud_cover": 13.598524,
    "sensor": "Sentinel-2"
  }
]